opentelemetry/semconv/__init__.py
opentelemetry/semconv/version.py
opentelemetry/semconv/resource/__init__.py
opentelemetry/semconv/trace/__init__.py
opentelemetry_semantic_conventions-0.33b0.dist-info/LICENSE
opentelemetry_semantic_conventions-0.33b0.dist-info/METADATA
opentelemetry_semantic_conventions-0.33b0.dist-info/WHEEL
opentelemetry_semantic_conventions-0.33b0.dist-info/top_level.txt
opentelemetry_semantic_conventions-0.33b0.dist-info/RECORD
